[
  {
    "address": "Vesterbrogade 20, 3. tv",
    "municipality": "Aalborg",
    "postal_code": "9000",
    "price": 1875000,
    "sqm": 78,
    "listing_date": "2026-07-01",
    "listing_source": "boligsiden",
    "external_id": "bs-mock-9001",
    "lat": 57.0470,
    "lon": 9.9150,
    "status": "active",
    "building_year": 1962,
    "property_type": "apartment",
    "rooms": 3,
    "image_urls": [],
    "description": "Mock listing used while CRAWL_MOCK_MODE is enabled.",
    "agent_name": "Nybolig Aalborg"
  },
  {
    "address": "Skovbakken 14",
    "municipality": "Aarhus",
    "postal_code": "8000",
    "price": 3450000,
    "sqm": 150,
    "listing_date": "2026-06-28",
    "listing_source": "boligsiden",
    "external_id": "bs-mock-9002",
    "lat": 56.1620,
    "lon": 10.1980,
    "status": "active",
    "building_year": 1979,
    "property_type": "villa",
    "rooms": 5,
    "image_urls": [],
    "description": "Mock listing used while CRAWL_MOCK_MODE is enabled.",
    "agent_name": "Home Aarhus"
  },
  {
    "address": "Amagerbrogade 55, 2. th",
    "municipality": "København",
    "postal_code": "2300",
    "price": 2950000,
    "sqm": 68,
    "listing_date": "2026-07-05",
    "listing_source": "boligsiden",
    "external_id": "bs-mock-9003",
    "lat": 55.6650,
    "lon": 12.5960,
    "status": "active",
    "building_year": 1934,
    "property_type": "apartment",
    "rooms": 3,
    "image_urls": [],
    "description": "Mock listing used while CRAWL_MOCK_MODE is enabled.",
    "agent_name": "EDC Amager"
  }
]
